rdm6300/__init__.py
rdm6300/reader.py
rdm6300/test_reader.py
rdm6300-0.1.1.dist-info/LICENSE
rdm6300-0.1.1.dist-info/METADATA
rdm6300-0.1.1.dist-info/WHEEL
rdm6300-0.1.1.dist-info/top_level.txt
rdm6300-0.1.1.dist-info/RECORD
