Metadata-Version: 2.1
Name: rdm6300
Version: 0.1.1
Summary: RDM6300/EM4100 RFID reader library
Home-page: https://github.com/mad-tinkerer/python-rdm6300
Author: The Mad Thinkerer Me
Author-email: mad.tiknerer.me@gmail.com
License: UNKNOWN
Platform: UNKNOWN
Classifier: Programming Language :: Python :: 3
Classifier: Programming Language :: Python :: 2
Classifier: License :: OSI Approved :: MIT License
Classifier: Operating System :: OS Independent
Requires-Dist: pyserial
